{
  "Keells Super": {
    "ads": [
      {
        "id": "1844100109581098",
        "brand": "Keells Super",
        "page_name": "Keells Super",
        "start_date": "Feb 14, 2026",
        "platforms": [],
        "text_preview": "6 ads use this creative and text",
        "status": "active",
        "ad_snapshot_url": "https://www.facebook.com/ads/library/?id=1844100109581098",
        "has_real_id": true,
        "scraped_at": "2026-04-10T03:48:04.158972"
      },
      {
        "id": "882125124699199",
        "brand": "Keells Super",
        "page_name": "Keells Super",
        "start_date": "Apr 1, 2026",
        "platforms": [],
        "text_preview": "Power your day & boost your chance to win! 💚",
        "status": "active",
        "ad_snapshot_url": "https://www.facebook.com/ads/library/?id=882125124699199",
        "has_real_id": true,
        "scraped_at": "2026-04-10T03:48:04.158999"
      },
      {
        "id": "1220675956532641",
        "brand": "Keells Super",
        "page_name": "Keells Super",
        "start_date": "Feb 12, 2026",
        "platforms": [],
        "text_preview": "10 ads use this creative and text",
        "status": "active",
        "ad_snapshot_url": "https://www.facebook.com/ads/library/?id=1220675956532641",
        "has_real_id": true,
        "scraped_at": "2026-04-10T03:48:04.159017"
      },
      {
        "id": "26504057342543982",
        "brand": "Keells Super",
        "page_name": "Keells Super",
        "start_date": "Apr 5, 2026",
        "platforms": [],
        "text_preview": "8 ads use this creative and text",
        "status": "active",
        "ad_snapshot_url": "https://www.facebook.com/ads/library/?id=26504057342543982",
        "has_real_id": true,
        "scraped_at": "2026-04-10T03:48:04.159031"
      },
      {
        "id": "1220437816391532",
        "brand": "Keells Super",
        "page_name": "Keells Super",
        "start_date": "Mar 23, 2026",
        "platforms": [],
        "text_preview": "11 ads use this creative and text",
        "status": "active",
        "ad_snapshot_url": "https://www.facebook.com/ads/library/?id=1220437816391532",
        "has_real_id": true,
        "scraped_at": "2026-04-10T03:48:04.159042"
      },
      {
        "id": "1391277516087641",
        "brand": "Keells Super",
        "page_name": "Keells Super",
        "start_date": "Feb 13, 2026",
        "platforms": [],
        "text_preview": "Never without Keells Nexus - the app that rewards how you shop.📱",
        "status": "active",
        "ad_snapshot_url": "https://www.facebook.com/ads/library/?id=1391277516087641",
        "has_real_id": true,
        "scraped_at": "2026-04-10T03:48:04.159058"
      },
      {
        "id": "1627753298474294",
        "brand": "Keells Super",
        "page_name": "Keells Super",
        "start_date": "Apr 1, 2026",
        "platforms": [],
        "text_preview": "3 ads use this creative and text",
        "status": "active",
        "ad_snapshot_url": "https://www.facebook.com/ads/library/?id=1627753298474294",
        "has_real_id": true,
        "scraped_at": "2026-04-10T03:48:04.159068"
      },
      {
        "id": "913955014945681",
        "brand": "Keells Super",
        "page_name": "Keells Super",
        "start_date": "Apr 3, 2026",
        "platforms": [],
        "text_preview": "Weekend cravings? We’ve cooked up the perfect deals just for you! 🔥🍴",
        "status": "active",
        "ad_snapshot_url": "https://www.facebook.com/ads/library/?id=913955014945681",
        "has_real_id": true,
        "scraped_at": "2026-04-10T03:48:04.159080"
      },
      {
        "id": "1279899787466653",
        "brand": "Keells Super",
        "page_name": "Keells Super",
        "start_date": "Mar 25, 2026",
        "platforms": [],
        "text_preview": "Ready for a getaway? ✈️",
        "status": "active",
        "ad_snapshot_url": "https://www.facebook.com/ads/library/?id=1279899787466653",
        "has_real_id": true,
        "scraped_at": "2026-04-10T03:48:04.159091"
      },
      {
        "id": "975756331688688",
        "brand": "Keells Super",
        "page_name": "Keells Super",
        "start_date": "Apr 2, 2026",
        "platforms": [],
        "text_preview": "Your favourites, all in one stop",
        "status": "active",
        "ad_snapshot_url": "https://www.facebook.com/ads/library/?id=975756331688688",
        "has_real_id": true,
        "scraped_at": "2026-04-10T03:48:04.159107"
      },
      {
        "id": "2423437091462527",
        "brand": "Keells Super",
        "page_name": "Keells Super",
        "start_date": "Apr 2, 2026",
        "platforms": [],
        "text_preview": "3 ads use this creative and text",
        "status": "active",
        "ad_snapshot_url": "https://www.facebook.com/ads/library/?id=2423437091462527",
        "has_real_id": true,
        "scraped_at": "2026-04-10T03:48:04.159118"
      },
      {
        "id": "1241979111390158",
        "brand": "Keells Super",
        "page_name": "Keells Super",
        "start_date": "Apr 7, 2026",
        "platforms": [],
        "text_preview": "Hungry for a good deal? 👀🔥",
        "status": "active",
        "ad_snapshot_url": "https://www.facebook.com/ads/library/?id=1241979111390158",
        "has_real_id": true,
        "scraped_at": "2026-04-10T03:48:04.159129"
      },
      {
        "id": "882262671530216",
        "brand": "Keells Super",
        "page_name": "Keells Super",
        "start_date": "Mar 18, 2026",
        "platforms": [],
        "text_preview": "Ever struggled without Wi-Fi to stay connected? That’s exactly how shopping feels without Keells Nexus.",
        "status": "active",
        "ad_snapshot_url": "https://www.facebook.com/ads/library/?id=882262671530216",
        "has_real_id": true,
        "scraped_at": "2026-04-10T03:48:04.159140"
      },
      {
        "id": "4401226536778561",
        "brand": "Keells Super",
        "page_name": "Keells Super",
        "start_date": "Feb 12, 2026",
        "platforms": [],
        "text_preview": "",
        "status": "active",
        "ad_snapshot_url": "https://www.facebook.com/ads/library/?id=4401226536778561",
        "scraped_at": "2026-04-10T03:48:04.340813"
      },
      {
        "id": "1492130112271102",
        "brand": "Keells Super",
        "page_name": "Keells Super",
        "start_date": "Apr 5, 2026",
        "platforms": [],
        "text_preview": "",
        "status": "active",
        "ad_snapshot_url": "https://www.facebook.com/ads/library/?id=1492130112271102",
        "scraped_at": "2026-04-10T03:48:04.340815"
      },
      {
        "id": "2740136226346140",
        "brand": "Keells Super",
        "page_name": "Keells Super",
        "start_date": "Mar 23, 2026",
        "platforms": [],
        "text_preview": "",
        "status": "active",
        "ad_snapshot_url": "https://www.facebook.com/ads/library/?id=2740136226346140",
        "scraped_at": "2026-04-10T03:48:04.340817"
      },
      {
        "id": "890851960582667",
        "brand": "Keells Super",
        "page_name": "Keells Super",
        "start_date": "Feb 13, 2026",
        "platforms": [],
        "text_preview": "",
        "status": "active",
        "ad_snapshot_url": "https://www.facebook.com/ads/library/?id=890851960582667",
        "scraped_at": "2026-04-10T03:48:04.340818"
      },
      {
        "id": "1299813688911985",
        "brand": "Keells Super",
        "page_name": "Keells Super",
        "start_date": "Apr 3, 2026",
        "platforms": [],
        "text_preview": "",
        "status": "active",
        "ad_snapshot_url": "https://www.facebook.com/ads/library/?id=1299813688911985",
        "scraped_at": "2026-04-10T03:48:04.340822"
      },
      {
        "id": "26310751458606220",
        "brand": "Keells Super",
        "page_name": "Keells Super",
        "start_date": "Mar 25, 2026",
        "platforms": [],
        "text_preview": "",
        "status": "active",
        "ad_snapshot_url": "https://www.facebook.com/ads/library/?id=26310751458606220",
        "scraped_at": "2026-04-10T03:48:04.340823"
      },
      {
        "id": "1278855980859802",
        "brand": "Keells Super",
        "page_name": "Keells Super",
        "start_date": "Mar 31, 2026",
        "platforms": [],
        "text_preview": "",
        "status": "active",
        "ad_snapshot_url": "https://www.facebook.com/ads/library/?id=1278855980859802",
        "scraped_at": "2026-04-10T03:48:04.340831"
      },
      {
        "id": "1405730267521291",
        "brand": "Keells Super",
        "page_name": "Keells Super",
        "start_date": null,
        "platforms": [],
        "text_preview": "",
        "status": "active",
        "ad_snapshot_url": "https://www.facebook.com/ads/library/?id=1405730267521291",
        "scraped_at": "2026-04-10T03:48:04.340833"
      },
      {
        "id": "1338782825111351",
        "brand": "Keells Super",
        "page_name": "Keells Super",
        "start_date": null,
        "platforms": [],
        "text_preview": "",
        "status": "active",
        "ad_snapshot_url": "https://www.facebook.com/ads/library/?id=1338782825111351",
        "scraped_at": "2026-04-10T03:48:04.340838"
      },
      {
        "id": "1623903648792915",
        "brand": "Keells Super",
        "page_name": "Keells Super",
        "start_date": null,
        "platforms": [],
        "text_preview": "",
        "status": "active",
        "ad_snapshot_url": "https://www.facebook.com/ads/library/?id=1623903648792915",
        "scraped_at": "2026-04-10T03:48:04.340839"
      },
      {
        "id": "1273595094218516",
        "brand": "Keells Super",
        "page_name": "Keells Super",
        "start_date": null,
        "platforms": [],
        "text_preview": "",
        "status": "active",
        "ad_snapshot_url": "https://www.facebook.com/ads/library/?id=1273595094218516",
        "scraped_at": "2026-04-10T03:48:04.340846"
      },
      {
        "id": "1532764041114976",
        "brand": "Keells Super",
        "page_name": "Keells Super",
        "start_date": null,
        "platforms": [],
        "text_preview": "",
        "status": "active",
        "ad_snapshot_url": "https://www.facebook.com/ads/library/?id=1532764041114976",
        "scraped_at": "2026-04-10T03:48:04.340847"
      },
      {
        "id": "ad_607901",
        "brand": "Keells Super",
        "page_name": "Keells Super",
        "start_date": "Mar 31, 2026",
        "platforms": [],
        "text_preview": "Power your day & boost your chance to win!",
        "status": "active",
        "ad_snapshot_url": null,
        "has_real_id": false,
        "scraped_at": "2026-04-10T03:48:04.159156"
      }
    ],
    "count": 26,
    "page_id": "108836225822670",
    "source_url": "https://www.facebook.com/ads/library/?active_status=active&ad_type=all&country=LK&is_targeted_country=false&media_type=all&search_type=page&sort_data[direction]=desc&sort_data[mode]=total_impressions&view_all_page_id=108836225822670",
    "collected_at": "2026-04-10T03:48:04.383082"
  },
  "Cargills Food City": {
    "ads": [
      {
        "id": "1681245556389261",
        "brand": "Cargills Food City",
        "page_name": "Cargills Food City",
        "start_date": "Mar 22, 2026",
        "platforms": [],
        "text_preview": "Get all your Cetaphil essentials in one place with 15% off!",
        "status": "active",
        "ad_snapshot_url": "https://www.facebook.com/ads/library/?id=1681245556389261",
        "has_real_id": true,
        "scraped_at": "2026-04-10T03:48:49.171390"
      },
      {
        "id": "773047822339274",
        "brand": "Cargills Food City",
        "page_name": "Cargills Food City",
        "start_date": "Apr 3, 2026",
        "platforms": [],
        "text_preview": "මේ උත්සව සමයේ රු මිලියන 40ක තෑගි දිනාගන්න ඔබ සූදානම්ද?",
        "status": "active",
        "ad_snapshot_url": "https://www.facebook.com/ads/library/?id=773047822339274",
        "has_real_id": true,
        "scraped_at": "2026-04-10T03:48:49.171424"
      },
      {
        "id": "26460196883592928",
        "brand": "Cargills Food City",
        "page_name": "Cargills Food City",
        "start_date": "Apr 3, 2026",
        "platforms": [],
        "text_preview": "புத்தாண்டை 40 மில்லியன் ரூபாவுடன் கொண்டாடி மகிழுங்கள்!",
        "status": "active",
        "ad_snapshot_url": "https://www.facebook.com/ads/library/?id=26460196883592928",
        "has_real_id": true,
        "scraped_at": "2026-04-10T03:48:49.171439"
      },
      {
        "id": "2208151603322307",
        "brand": "Cargills Food City",
        "page_name": "Cargills Food City",
        "start_date": "Apr 3, 2026",
        "platforms": [],
        "text_preview": "Experience the scrumptious crunch of the world’s best wafer with Loacker!",
        "status": "active",
        "ad_snapshot_url": "https://www.facebook.com/ads/library/?id=2208151603322307",
        "has_real_id": true,
        "scraped_at": "2026-04-10T03:48:49.171459"
      },
      {
        "id": "1336137501657723",
        "brand": "Cargills Food City",
        "page_name": "Cargills Food City",
        "start_date": "Apr 3, 2026",
        "platforms": [],
        "text_preview": "",
        "status": "active",
        "ad_snapshot_url": "https://www.facebook.com/ads/library/?id=1336137501657723",
        "scraped_at": "2026-04-10T03:48:49.295119"
      },
      {
        "id": "ad_574005",
        "brand": "Cargills Food City",
        "page_name": "Cargills Food City",
        "start_date": "Apr 3, 2026",
        "platforms": [],
        "text_preview": "Congratulations to our Bill Wipeout winner!",
        "status": "active",
        "ad_snapshot_url": null,
        "has_real_id": false,
        "scraped_at": "2026-04-10T03:48:49.171475"
      }
    ],
    "count": 6,
    "page_id": "155866468723",
    "source_url": "https://www.facebook.com/ads/library/?active_status=active&ad_type=all&country=LK&is_targeted_country=false&media_type=all&search_type=page&sort_data[mode]=total_impressions&sort_data[direction]=desc&view_all_page_id=155866468723",
    "collected_at": "2026-04-10T03:48:49.333673"
  },
  "Softlogic Glomark": {
    "ads": [
      {
        "id": "882181888177006",
        "brand": "Softlogic Glomark",
        "page_name": "Softlogic Glomark",
        "start_date": "Apr 1, 2026",
        "platforms": [],
        "text_preview": "2 ads use this creative and text",
        "status": "active",
        "ad_snapshot_url": "https://www.facebook.com/ads/library/?id=882181888177006",
        "has_real_id": true,
        "scraped_at": "2026-04-10T03:49:34.216974"
      },
      {
        "id": "2023422438555119",
        "brand": "Softlogic Glomark",
        "page_name": "Softlogic Glomark",
        "start_date": "Apr 6, 2026",
        "platforms": [],
        "text_preview": "Take Home Better Discounts with Softlogic GLOMARK from 06th to 12th April 2026!",
        "status": "active",
        "ad_snapshot_url": "https://www.facebook.com/ads/library/?id=2023422438555119",
        "has_real_id": true,
        "scraped_at": "2026-04-10T03:49:34.217001"
      },
      {
        "id": "1624380855258453",
        "brand": "Softlogic Glomark",
        "page_name": "Softlogic Glomark",
        "start_date": "Apr 9, 2026 · Total active time 15 hrs",
        "platforms": [],
        "text_preview": "ගෙට BETTER AVURUDU with 20% OFF on your Total Bill when you pay with Nations Trust Bank Credit Cards at all GLOMARK outlets including Essentials & glomark.lk on 10th April 2026.",
        "status": "active",
        "ad_snapshot_url": "https://www.facebook.com/ads/library/?id=1624380855258453",
        "has_real_id": true,
        "scraped_at": "2026-04-10T03:49:34.217019"
      },
      {
        "id": "1713092729857334",
        "brand": "Softlogic Glomark",
        "page_name": "Softlogic Glomark",
        "start_date": "Apr 1, 2026",
        "platforms": [],
        "text_preview": "ගෙට BETTER AVURUDU 2026!",
        "status": "active",
        "ad_snapshot_url": "https://www.facebook.com/ads/library/?id=1713092729857334",
        "has_real_id": true,
        "scraped_at": "2026-04-10T03:49:34.217032"
      },
      {
        "id": "1634351071051016",
        "brand": "Softlogic Glomark",
        "page_name": "Softlogic Glomark",
        "start_date": "Apr 8, 2026",
        "platforms": [],
        "text_preview": "Experience the sacred පුණ්‍ය කාලය from 3:08 AM to 3:56 PM on Tuesday, April 14th 2026.",
        "status": "active",
        "ad_snapshot_url": "https://www.facebook.com/ads/library/?id=1634351071051016",
        "has_real_id": true,
        "scraped_at": "2026-04-10T03:49:34.217044"
      },
      {
        "id": "1642273843463983",
        "brand": "Softlogic Glomark",
        "page_name": "Softlogic Glomark",
        "start_date": "Apr 9, 2026 · Total active time 22 hrs",
        "platforms": [],
        "text_preview": "Welcome the Sinhala & Tamil New Year at 9:32 AM on Tuesday, April 14.",
        "status": "active",
        "ad_snapshot_url": "https://www.facebook.com/ads/library/?id=1642273843463983",
        "has_real_id": true,
        "scraped_at": "2026-04-10T03:49:34.217055"
      },
      {
        "id": "1282855497122158",
        "brand": "Softlogic Glomark",
        "page_name": "Softlogic Glomark",
        "start_date": "Apr 9, 2026 · Total active time 17 hrs",
        "platforms": [],
        "text_preview": "That “oops, we ran out” moment? Not this season…",
        "status": "active",
        "ad_snapshot_url": "https://www.facebook.com/ads/library/?id=1282855497122158",
        "has_real_id": true,
        "scraped_at": "2026-04-10T03:49:34.217067"
      },
      {
        "id": "2084952532049164",
        "brand": "Softlogic Glomark",
        "page_name": "Softlogic Glomark",
        "start_date": "Apr 9, 2026 · Total active time 16 hrs",
        "platforms": [],
        "text_preview": "\"ලෙන්චිනෝ... Softlogic GLOMARK එක්ක මේ සැරෙත් ගෙට better අවුරුදු!\"",
        "status": "active",
        "ad_snapshot_url": "https://www.facebook.com/ads/library/?id=2084952532049164",
        "has_real_id": true,
        "scraped_at": "2026-04-10T03:49:34.217085"
      },
      {
        "id": "2577243742677851",
        "brand": "Softlogic Glomark",
        "page_name": "Softlogic Glomark",
        "start_date": "Apr 9, 2026 · Total active time 9 hrs",
        "platforms": [],
        "text_preview": "ගෙට BETTER AVURUDU with 25% off with HNB Credit Cards and 15% off with HNB Debit Cards on 10th & 24th April 2026. Discount is valid on the Supermarket Bill for purchases made online via www.glomark.lk throughout the day or at any GLOMARK outlet (3 PM - 8 PM)",
        "status": "active",
        "ad_snapshot_url": "https://www.facebook.com/ads/library/?id=2577243742677851",
        "has_real_id": true,
        "scraped_at": "2026-04-10T03:49:34.217105"
      },
      {
        "id": "1303177215045149",
        "brand": "Softlogic Glomark",
        "page_name": "Softlogic Glomark",
        "start_date": "Apr 1, 2026",
        "platforms": [],
        "text_preview": "",
        "status": "active",
        "ad_snapshot_url": "https://www.facebook.com/ads/library/?id=1303177215045149",
        "scraped_at": "2026-04-10T03:49:34.355312"
      },
      {
        "id": "1662455381630397",
        "brand": "Softlogic Glomark",
        "page_name": "Softlogic Glomark",
        "start_date": "Apr 9, 2026",
        "platforms": [],
        "text_preview": "",
        "status": "active",
        "ad_snapshot_url": "https://www.facebook.com/ads/library/?id=1662455381630397",
        "scraped_at": "2026-04-10T03:49:34.355339"
      },
      {
        "id": "ad_504215",
        "brand": "Softlogic Glomark",
        "page_name": "Softlogic Glomark",
        "start_date": "Apr 9, 2026 · Total active time 9 hrs",
        "platforms": [],
        "text_preview": "ගෙට BETTER AVURUDU with 25% DISCOUNT from People’s Bank Credit Cards and 10% DISCOUNT from People's Bank Debit Cards on your Supermarket Bill, every Friday until 30th April 2026. Shop online via www.glomark.lk or at any GLOMARK outlet.",
        "status": "active",
        "ad_snapshot_url": null,
        "has_real_id": false,
        "scraped_at": "2026-04-10T03:49:34.217126"
      }
    ],
    "count": 12,
    "page_id": "354233975342508",
    "source_url": "https://www.facebook.com/ads/library/?active_status=active&ad_type=all&country=LK&is_targeted_country=false&media_type=all&search_type=page&sort_data[direction]=desc&sort_data[mode]=total_impressions&view_all_page_id=354233975342508",
    "collected_at": "2026-04-10T03:49:34.394503"
  },
  "SPAR Sri Lanka": {
    "ads": [
      {
        "id": "818086711377348",
        "brand": "SPAR Sri Lanka",
        "page_name": "SPAR Sri Lanka",
        "start_date": "Apr 9, 2026 · Total active time 11 hrs",
        "platforms": [],
        "text_preview": "2 ads use this creative and text",
        "status": "active",
        "ad_snapshot_url": "https://www.facebook.com/ads/library/?id=818086711377348",
        "has_real_id": true,
        "scraped_at": "2026-04-10T03:50:19.203182"
      },
      {
        "id": "930603949954341",
        "brand": "SPAR Sri Lanka",
        "page_name": "SPAR Sri Lanka",
        "start_date": "Apr 9, 2026",
        "platforms": [],
        "text_preview": "",
        "status": "active",
        "ad_snapshot_url": "https://www.facebook.com/ads/library/?id=930603949954341",
        "scraped_at": "2026-04-10T03:50:19.326904"
      },
      {
        "id": "981469780974179",
        "brand": "SPAR Sri Lanka",
        "page_name": "SPAR Sri Lanka",
        "start_date": null,
        "platforms": [],
        "text_preview": "",
        "status": "active",
        "ad_snapshot_url": "https://www.facebook.com/ads/library/?id=981469780974179",
        "scraped_at": "2026-04-10T03:50:19.326921"
      },
      {
        "id": "ad_966218",
        "brand": "SPAR Sri Lanka",
        "page_name": "SPAR Sri Lanka",
        "start_date": "Apr 9, 2026 · Total active time 11 hrs",
        "platforms": [],
        "text_preview": "SPAR නෑගම් යන අලුත් විදිහ!",
        "status": "active",
        "ad_snapshot_url": null,
        "has_real_id": false,
        "scraped_at": "2026-04-10T03:50:19.203214"
      }
    ],
    "count": 4,
    "page_id": "290159608091322",
    "source_url": "https://www.facebook.com/ads/library/?active_status=active&ad_type=all&country=LK&is_targeted_country=false&media_type=all&search_type=page&sort_data[direction]=desc&sort_data[mode]=total_impressions&view_all_page_id=290159608091322",
    "collected_at": "2026-04-10T03:50:19.363503"
  }
}